DeepCheck/__init__.py
DeepCheck/aws_env.json
DeepCheck/aws_s3_d.py
DeepCheck/deepcheck.py
DeepCheck/environment.yml
DeepCheck/get_multi_identity_videos.py
DeepCheck/utils.py
DeepCheck/config/__init__.py
DeepCheck/config/baseline.yaml
DeepCheck/config/convolutional_timesformer.yaml
DeepCheck/config/size_invariant_timesformer.yaml
DeepCheck/config/slowfast.yaml
DeepCheck/models/__init__.py
DeepCheck/models/baseline.py
DeepCheck/models/convolutional_timesformer_base.py
DeepCheck/models/size_invariant_timesformer.py
DeepCheck/models/utils.py
DeepCheck/models/xception.py
DeepCheck/models/efficientnet/hubconf.py
DeepCheck/models/efficientnet/sotabench.py
DeepCheck/models/efficientnet/efficientnet_pytorch/__init__.py
DeepCheck/models/efficientnet/efficientnet_pytorch/model.py
DeepCheck/models/efficientnet/efficientnet_pytorch/utils.py
DeepCheck/models/efficientnet/tf_to_pytorch/convert_tf_to_pt/load_tf_weights.py
DeepCheck/models/efficientnet/tf_to_pytorch/convert_tf_to_pt/load_tf_weights_tf1.py
DeepCheck/models/efficientnet/tf_to_pytorch/convert_tf_to_pt/original_tf/__init__.py
DeepCheck/models/efficientnet/tf_to_pytorch/convert_tf_to_pt/original_tf/efficientnet_builder.py
DeepCheck/models/efficientnet/tf_to_pytorch/convert_tf_to_pt/original_tf/efficientnet_model.py
DeepCheck/models/efficientnet/tf_to_pytorch/convert_tf_to_pt/original_tf/eval_ckpt_main.py
DeepCheck/models/efficientnet/tf_to_pytorch/convert_tf_to_pt/original_tf/eval_ckpt_main_tf1.py
DeepCheck/models/efficientnet/tf_to_pytorch/convert_tf_to_pt/original_tf/preprocessing.py
DeepCheck/models/efficientnet/tf_to_pytorch/convert_tf_to_pt/original_tf/utils.py
DeepCheck/preprocessing/__init__.py
DeepCheck/preprocessing/face_detector.py
DeepCheck/preprocessing/faces_dataset.py
DeepCheck/preprocessing/utils.py
DeepCheck/pretrained/__init__.py
DeepCheck/transforms/__init__.py
DeepCheck/transforms/albu.py
fake_check-0.0.1.dist-info/METADATA
fake_check-0.0.1.dist-info/WHEEL
fake_check-0.0.1.dist-info/top_level.txt
fake_check-0.0.1.dist-info/RECORD
