Metadata-Version: 2.1
Name: fake-check
Version: 0.0.1
Summary: baseline deepcheck module
Home-page: https://github.com/SANJITH-KUMAR-20/SizeInvariantTransformer-for-Deepfake-detection
Author: PhospheneAI
Author-email: sanjith.kumar@phospheneai.com
Classifier: Programming Language :: Python :: 3.11
Requires-Python: >=3.11
Requires-Dist: albumentations ==1.4.0
Requires-Dist: annotated-types ==0.6.0
Requires-Dist: anyio ==4.3.0
Requires-Dist: asttokens ==2.4.1
Requires-Dist: av ==11.0.0
Requires-Dist: boto3 ==1.34.56
Requires-Dist: botocore ==1.34.56
Requires-Dist: certifi ==2024.2.2
Requires-Dist: charset-normalizer ==3.3.2
Requires-Dist: click ==8.1.7
Requires-Dist: colorama ==0.4.6
Requires-Dist: comm ==0.2.1
Requires-Dist: contourpy ==1.2.0
Requires-Dist: cycler ==0.12.1
Requires-Dist: debugpy ==1.8.1
Requires-Dist: decorator ==4.4.2
Requires-Dist: efficientnet-pytorch ==0.7.1
Requires-Dist: einops ==0.7.0
Requires-Dist: executing ==2.0.1
Requires-Dist: facenet-pytorch ==2.5.3
Requires-Dist: fastapi ==0.110.0
Requires-Dist: filelock ==3.13.1
Requires-Dist: fonttools ==4.49.0
Requires-Dist: fsspec ==2024.2.0
Requires-Dist: fvcore ==0.1.5.post20221221
Requires-Dist: h11 ==0.14.0
Requires-Dist: huggingface-hub ==0.20.3
Requires-Dist: idna ==3.6
Requires-Dist: imageio ==2.34.0
Requires-Dist: imageio-ffmpeg ==0.4.9
Requires-Dist: iopath ==0.1.10
Requires-Dist: ipykernel ==6.29.2
Requires-Dist: ipython ==8.22.1
Requires-Dist: jedi ==0.19.1
Requires-Dist: Jinja2 ==3.1.3
Requires-Dist: jmespath ==1.0.1
Requires-Dist: joblib ==1.3.2
Requires-Dist: jupyter-client ==8.6.0
Requires-Dist: jupyter-core ==5.7.1
Requires-Dist: kiwisolver ==1.4.5
Requires-Dist: lazy-loader ==0.3
Requires-Dist: MarkupSafe ==2.1.5
Requires-Dist: matplotlib ==3.8.3
Requires-Dist: matplotlib-inline ==0.1.6
Requires-Dist: moviepy ==1.0.3
Requires-Dist: mpmath ==1.3.0
Requires-Dist: nest-asyncio ==1.6.0
Requires-Dist: networkx ==3.2.1
Requires-Dist: numpy ==1.26.4
Requires-Dist: opencv-python ==4.9.0.80
Requires-Dist: opencv-python-headless ==4.9.0.80
Requires-Dist: packaging ==23.2
Requires-Dist: parameterized ==0.9.0
Requires-Dist: parso ==0.8.3
Requires-Dist: pillow ==10.2.0
Requires-Dist: platformdirs ==4.2.0
Requires-Dist: portalocker ==2.8.2
Requires-Dist: proglog ==0.1.10
Requires-Dist: prompt-toolkit ==3.0.43
Requires-Dist: psutil ==5.9.8
Requires-Dist: pure-eval ==0.2.2
Requires-Dist: pydantic ==2.6.2
Requires-Dist: pydantic-core ==2.16.3
Requires-Dist: Pygments ==2.17.2
Requires-Dist: pyparsing ==3.1.1
Requires-Dist: python-dateutil ==2.8.2
Requires-Dist: python-multipart ==0.0.9
Requires-Dist: pytorchvideo ==0.1.5
Requires-Dist: pytube ==15.0.0
Requires-Dist: pywin32 ==306
Requires-Dist: PyYAML ==6.0.1
Requires-Dist: pyzmq ==25.1.2
Requires-Dist: qudida ==0.0.4
Requires-Dist: requests ==2.31.0
Requires-Dist: s3transfer ==0.10.0
Requires-Dist: safetensors ==0.4.2
Requires-Dist: scikit-image ==0.22.0
Requires-Dist: scikit-learn ==1.4.1.post1
Requires-Dist: scipy ==1.12.0
Requires-Dist: six ==1.16.0
Requires-Dist: sniffio ==1.3.0
Requires-Dist: stack-data ==0.6.3
Requires-Dist: starlette ==0.36.3
Requires-Dist: sympy ==1.12
Requires-Dist: tabulate ==0.9.0
Requires-Dist: termcolor ==2.4.0
Requires-Dist: threadpoolctl ==3.3.0
Requires-Dist: tifffile ==2024.2.12
Requires-Dist: timm ==0.9.16
Requires-Dist: torch ==2.2.1+cu118
Requires-Dist: torchaudio ==2.2.1+cu118
Requires-Dist: torchsummary ==1.5.1
Requires-Dist: torchvision ==0.17.1
Requires-Dist: tornado ==6.4
Requires-Dist: tqdm ==4.66.2
Requires-Dist: traitlets ==5.14.1
Requires-Dist: typing-extensions ==4.9.0
Requires-Dist: urllib3 ==2.0.7
Requires-Dist: uvicorn ==0.27.1
Requires-Dist: wcwidth ==0.2.13
Requires-Dist: yacs ==0.1.8
